jupyterlab_tabular_data_viewer_extension/__init__.py
jupyterlab_tabular_data_viewer_extension/_version.py
jupyterlab_tabular_data_viewer_extension/routes.py
jupyterlab_tabular_data_viewer_extension/stats.py
jupyterlab_tabular_data_viewer_extension/tests/__init__.py
jupyterlab_tabular_data_viewer_extension/tests/test_routes.py
jupyterlab_tabular_data_viewer_extension-1.4.4.data/data/etc/jupyter/jupyter_server_config.d/jupyterlab_tabular_data_viewer_extension.json
jupyterlab_tabular_data_viewer_extension-1.4.4.data/data/share/jupyter/labextensions/jupyterlab_tabular_data_viewer_extension/package.json
jupyterlab_tabular_data_viewer_extension-1.4.4.data/data/share/jupyter/labextensions/jupyterlab_tabular_data_viewer_extension/schemas/jupyterlab_tabular_data_viewer_extension/package.json.orig
jupyterlab_tabular_data_viewer_extension-1.4.4.data/data/share/jupyter/labextensions/jupyterlab_tabular_data_viewer_extension/schemas/jupyterlab_tabular_data_viewer_extension/plugin.json
jupyterlab_tabular_data_viewer_extension-1.4.4.data/data/share/jupyter/labextensions/jupyterlab_tabular_data_viewer_extension/static/129.18b74018a90c87fc14c7.js
jupyterlab_tabular_data_viewer_extension-1.4.4.data/data/share/jupyter/labextensions/jupyterlab_tabular_data_viewer_extension/static/728.689b1fb386b5987b9d87.js
jupyterlab_tabular_data_viewer_extension-1.4.4.data/data/share/jupyter/labextensions/jupyterlab_tabular_data_viewer_extension/static/remoteEntry.49d148a0606614a02c1e.js
jupyterlab_tabular_data_viewer_extension-1.4.4.data/data/share/jupyter/labextensions/jupyterlab_tabular_data_viewer_extension/static/style.js
jupyterlab_tabular_data_viewer_extension-1.4.4.data/data/share/jupyter/labextensions/jupyterlab_tabular_data_viewer_extension/static/third-party-licenses.json
jupyterlab_tabular_data_viewer_extension-1.4.4.data/data/share/jupyter/labextensions/jupyterlab_tabular_data_viewer_extension/install.json
jupyterlab_tabular_data_viewer_extension-1.4.4.dist-info/METADATA
jupyterlab_tabular_data_viewer_extension-1.4.4.dist-info/WHEEL
jupyterlab_tabular_data_viewer_extension-1.4.4.dist-info/licenses/LICENSE
jupyterlab_tabular_data_viewer_extension-1.4.4.dist-info/RECORD
