Metadata-Version: 2.4
Name: jupyterlab_tabular_data_viewer_extension
Version: 1.4.4
Summary: Jupyterlab extension to browse tabular data files (Parquet, Excel, CSV, TSV) with filtering and sorting capabilities
Project-URL: Homepage, https://github.com/stellarshenson/jupyterlab_tabular_data_viewer_extension
Project-URL: Bug Tracker, https://github.com/stellarshenson/jupyterlab_tabular_data_viewer_extension/issues
Project-URL: Repository, https://github.com/stellarshenson/jupyterlab_tabular_data_viewer_extension.git
Author-email: Stellars Henson <konrad.jelen@gmail.com>
License: BSD 3-Clause License
License-File: LICENSE
Keywords: csv,excel,jupyter,jupyterlab,jupyterlab-extension,parquet,tabular-data,tsv
Classifier: Framework :: Jupyter
Classifier: Framework :: Jupyter :: JupyterLab
Classifier: Framework :: Jupyter :: JupyterLab :: 4
Classifier: Framework :: Jupyter :: JupyterLab :: Extensions
Classifier: Framework :: Jupyter :: JupyterLab :: Extensions :: Prebuilt
Classifier: License :: OSI Approved :: BSD License
Classifier: Programming Language :: Python
Classifier: Programming Language :: Python :: 3
Classifier: Programming Language :: Python :: 3.9
Classifier: Programming Language :: Python :: 3.10
Classifier: Programming Language :: Python :: 3.11
Classifier: Programming Language :: Python :: 3.12
Classifier: Programming Language :: Python :: 3.13
Requires-Python: >=3.9
Requires-Dist: openpyxl>=3.0.0
Requires-Dist: pandas>=1.5.0
Requires-Dist: pyarrow>=10.0.0
Provides-Extra: dev
Requires-Dist: jupyterlab>=4; extra == 'dev'
Provides-Extra: test
Requires-Dist: coverage; extra == 'test'
Requires-Dist: pytest; extra == 'test'
Requires-Dist: pytest-asyncio; extra == 'test'
Requires-Dist: pytest-cov; extra == 'test'
Requires-Dist: pytest-jupyter[server]>=0.6.0; extra == 'test'
